oleeaitoolkit/__init__.py
oleeaitoolkit/_version.py
oleeaitoolkit/cli.py
oleeaitoolkit/ai/__init__.py
oleeaitoolkit/ai/vercel_openai.py
oleeaitoolkit/cryptography/__init__.py
oleeaitoolkit/cryptography/decrypt_messages.py
oleeaitoolkit/logger/__init__.py
oleeaitoolkit/logger/logger.py
oleeaitoolkit/memory/__init__.py
oleeaitoolkit/memory/chat_history.py
oleeaitoolkit-0.4.0.dist-info/METADATA
oleeaitoolkit-0.4.0.dist-info/WHEEL
oleeaitoolkit-0.4.0.dist-info/entry_points.txt
oleeaitoolkit-0.4.0.dist-info/top_level.txt
oleeaitoolkit-0.4.0.dist-info/RECORD
