Metadata-Version: 2.4
Name: oleeaitoolkit
Version: 0.4.0
Summary: Toolkit with AI helpers and vector utilities
Author-email: Olee AI LLC <chamika.h@olee.ai>
License: MIT
Requires-Python: >=3.9
Requires-Dist: pydantic==2.12.4
Requires-Dist: openai==2.7.2
Requires-Dist: cryptography>=41.0.0
Requires-Dist: requests>=2.31.0
